modal_hj3415/.DS_Store
modal_hj3415/__init__.py
modal_hj3415/admin.py
modal_hj3415/apps.py
modal_hj3415/models.py
modal_hj3415/migrations/0001_initial.py
modal_hj3415/migrations/__init__.py
modal_hj3415/static/modal_hj3415/img/default_modal_bg.jpg
modal_hj3415/templates/modal_hj3415/_load.html
modal_hj3415/templates/modal_hj3415/_load_many.html
modal_hj3415/templates/modal_hj3415/image_only.html
modal_hj3415/templates/modal_hj3415/link_video.html
modal_hj3415/templates/modal_hj3415/rotate_bg.html
modal_hj3415/templates/modal_hj3415/single_bg.html
modal_hj3415/templatetags/__init__.py
modal_hj3415/templatetags/modal_tags.py
modal_hj3415-0.3.0.dist-info/WHEEL
modal_hj3415-0.3.0.dist-info/METADATA
modal_hj3415-0.3.0.dist-info/RECORD
