Metadata-Version: 2.4
Name: modal-hj3415
Version: 0.3.0
Summary: modal-hj3415 is the program for opening the modal window
Author-email: Hyungjin Kim <hj3415@gmail.com>
Classifier: License :: OSI Approved :: MIT License
Requires-Dist: django
Requires-Dist: Pillow
Project-URL: Home, https://www.hyungjin.kr
